Metadata-Version: 2.1
Name: simfast
Version: 0.0.2
Summary: A simple liberary to use fastai in easy way
Home-page: UNKNOWN
Author: Israr Ahmad
Author-email: israrbuaa@gmail.com
License: MIT
Platform: UNKNOWN
Classifier: Development Status :: 5 - Production/Stable
Classifier: Intended Audience :: Education
Classifier: Operating System :: Microsoft :: Windows :: Windows 10
Classifier: License :: OSI Approved :: MIT License
Classifier: Programming Language :: Python :: 3
License-File: LICENSE.txt
